pyESD/ESD_utils.py
pyESD/MLR_model.py
pyESD/Predictor_Base.py
pyESD/Predictor_Generator.py
pyESD/StationOperator.py
pyESD/Weatherstation.py
pyESD/__init__.py
pyESD/data_preprocess_utils.py
pyESD/dense_models.py
pyESD/ensemble_models.py
pyESD/feature_selection.py
pyESD/metrics.py
pyESD/models.py
pyESD/plot.py
pyESD/plot_utils.py
pyESD/predictand.py
pyESD/splitter.py
pyESD/standardizer.py
pyESD/teleconnections.py
tests/__init__.py
tests/preprocess_cmip5.py
tests/test_ensemble.py
tests/test_models.py
tests/test_pyESD.py
tests/test_pyESD_utils.py
tests/test_standardizer.py
tests/test_syn_data.py
tests/test_utils.py
pyESD-1.0.7.dist-info/AUTHORS.rst
pyESD-1.0.7.dist-info/LICENSE
pyESD-1.0.7.dist-info/METADATA
pyESD-1.0.7.dist-info/WHEEL
pyESD-1.0.7.dist-info/top_level.txt
pyESD-1.0.7.dist-info/RECORD
