Metadata-Version: 2.1
Name: pyESD
Version: 1.0.7
Summary: Python Package for Empirical Statistical Downscaling. pyESD is under active development and all colaborators are welcomed. The purpose of the package is to downscale any climate variables e.g. precipitation and temperature using predictors from  reanalysis datasets (eg. ERA5) to point scale. pyESD adopts many ML and AL as the transfer function. 
Home-page: https://github.com/Dan-Boat/PyESD
Author: Daniel Boateng
Author-email: dannboateng@gmail.com
License: MIT license
Keywords: pyESD Empirical Statistical Downscaling
Classifier: Development Status :: 2 - Pre-Alpha
Classifier: Intended Audience :: Developers
Classifier: License :: OSI Approved :: MIT License
Classifier: Natural Language :: English
Classifier: Programming Language :: Python :: 3
Classifier: Programming Language :: Python :: 3.7
Classifier: Programming Language :: Python :: 3.8
Classifier: Programming Language :: Python :: 3.9
Classifier: Programming Language :: Python :: 3.10
Requires-Python: >=3.7
License-File: LICENSE
License-File: AUTHORS.rst
Requires-Dist: cftime (>=1.6.0)
Requires-Dist: eofs (>=1.4)
Requires-Dist: geopandas (>=0.12)
Requires-Dist: numpy (>=1.21)
Requires-Dist: pandas (>=1.3)
Requires-Dist: scikit-learn (>=0.24)
Requires-Dist: scikit-optimize (>=0.9.0)
Requires-Dist: scipy (>=1.7)
Requires-Dist: seaborn (>=0.11)
Requires-Dist: tensorflow (>=2.8.0)
Requires-Dist: xarray (>=2023.1)
Requires-Dist: xgboost (>=1.5)
Requires-Dist: cycler (>=0.10)
Provides-Extra: dev
Requires-Dist: pip ; extra == 'dev'
Requires-Dist: bump2version ; extra == 'dev'
Requires-Dist: wheel ; extra == 'dev'
Requires-Dist: watchdog ; extra == 'dev'
Requires-Dist: flake8 ; extra == 'dev'
Requires-Dist: tox ; extra == 'dev'
Requires-Dist: coverage ; extra == 'dev'
Requires-Dist: Sphinx ; extra == 'dev'
Requires-Dist: twine ; extra == 'dev'
Requires-Dist: grip ; extra == 'dev'
Requires-Dist: pytest ; extra == 'dev'
Requires-Dist: pytest-cov ; extra == 'dev'
Requires-Dist: pytest-runner ; extra == 'dev'
Requires-Dist: netCDF4 ; extra == 'dev'
Requires-Dist: matplotlib ; extra == 'dev'
Requires-Dist: Sphinx-rtd-theme ; extra == 'dev'
Requires-Dist: setuptools ; extra == 'dev'
Requires-Dist: pydocstyle ; extra == 'dev'
Requires-Dist: packaging (>=21.3) ; extra == 'dev'
Requires-Dist: h5netcdf ; extra == 'dev'
Requires-Dist: importlib-metadata (>=4.4) ; extra == 'dev'
